easy_visualiser/__init__.py
easy_visualiser/helpers.py
easy_visualiser/key_mapping.py
easy_visualiser/maths.py
easy_visualiser/modal_control.py
easy_visualiser/modded_components.py
easy_visualiser/plugin_capability.py
easy_visualiser/ufunc.py
easy_visualiser/visualiser.py
easy_visualiser/visualiser_miscs.py
easy_visualiser/input/__init__.py
easy_visualiser/input/moos.py
easy_visualiser/input/msgx.py
easy_visualiser/input/plotmsg.py
easy_visualiser/input/remote_socket.py
easy_visualiser/input/ros.py
easy_visualiser/input/ros2.py
easy_visualiser/plugins/__init__.py
easy_visualiser/plugins/abstract_visualisable_plugin.py
easy_visualiser/plugins/functional_alternative_vis.py
easy_visualiser/plugins/functional_zscaler.py
easy_visualiser/plugins/visualisable_2D_lineplot.py
easy_visualiser/plugins/visualisable_3D_line.py
easy_visualiser/plugins/visualisable_axis.py
easy_visualiser/plugins/visualisable_displacementmap.py
easy_visualiser/plugins/visualisable_displacementmap_glob.py
easy_visualiser/plugins/visualisable_gridlines.py
easy_visualiser/plugins/visualisable_image.py
easy_visualiser/plugins/visualisable_mesh.py
easy_visualiser/plugins/visualisable_message_board.py
easy_visualiser/plugins/visualisable_points.py
easy_visualiser/plugins/visualisable_volumeplot.py
easy_visualiser/plugins/ext/__init__.py
easy_visualiser/plugins/ext/visualisable_axis_ruler.py
easy_visualiser/plugins/ext/visualisable_axis_with_bathy_offset.py
easy_visualiser/plugins/ext/visualisable_bathymetry.py
easy_visualiser/plugins/ext/visualisable_koz.py
easy_visualiser/plugins/ext/visualisable_moos_swarm.py
easy_visualiser/plugins/ext/visualisable_ocean_currents.py
easy_visualiser/plugins/ext/visualisable_planner_graph.py
easy_visualiser/plugins/ext/visualisable_planner_graph_moos.py
easy_visualiser/utils/__init__.py
easy_visualiser/utils/aggregator.py
easy_visualiser/utils/colour.py
easy_visualiser/utils/common.py
easy_visualiser/utils/dummy.py
easy_visualiser/utils/netcdf.py
easy_visualiser-0.2.0.dist-info/METADATA
easy_visualiser-0.2.0.dist-info/WHEEL
easy_visualiser-0.2.0.dist-info/top_level.txt
easy_visualiser-0.2.0.dist-info/RECORD
