Metadata-Version: 2.1
Name: easy-visualiser
Version: 0.2.0
Summary: Pluggable visualiser
Author: Tin Lai
Author-email: oscar@tinyiu.com
Classifier: Programming Language :: Python :: 3
Classifier: License :: OSI Approved :: MIT License
Classifier: Operating System :: OS Independent
Requires-Python: >=3.7
Requires-Dist: numpy
Requires-Dist: scipy
Requires-Dist: overrides
Requires-Dist: loguru
Requires-Dist: pyro5
Requires-Dist: vispy
Requires-Dist: pyqt6
Requires-Dist: typed-argument-parser
Requires-Dist: msgx ==1.0.3
Requires-Dist: pillow
